[
  {
    "location": "In House",
    "category": "Public",
    "orderNo": "admin12",
    "date": "2025-07-02",
    "type": "Client",
    "dismental": "Completed",
    "wind": "Started",
    "assemble": "Started",
    "testing": "Started",
    "siteLocation": "",
    "client": "",
    "typeOfJob": "",
    "otherJobType": "",
    "fieldJobDetails": [
      {
        "kva": "",
        "srNo": "",
        "rating": "",
        "note": ""
      }
    ],
    "execution": "",
    "jobCompletionCertificate": null,
    "delivery": true,
    "id": "1753827666240",
    "updatedAt": "2025-08-18T00:30:39.873Z"
  },
  {
    "location": "In House",
    "category": "Public",
    "orderNo": "orderchek",
    "date": "2025-08-13",
    "type": "Division",
    "dismental": "Started",
    "wind": "Completed",
    "assemble": "Started",
    "testing": "Completed",
    "siteLocation": "",
    "client": "",
    "typeOfJob": "",
    "otherJobType": "",
    "fieldJobDetails": [
      {
        "kva": "",
        "srNo": "",
        "rating": "",
        "note": ""
      }
    ],
    "execution": "",
    "jobCompletionCertificate": null,
    "delivery": false,
    "id": "1754950311220"
  },
  {
    "location": "Site",
    "category": "Private",
    "orderNo": "34567",
    "date": "2025-08-28",
    "type": "Division",
    "dismental": "",
    "wind": "",
    "assemble": "",
    "testing": "",
    "siteLocation": "asadf",
    "client": "fdxrftfgf",
    "typeOfJob": "Maintain",
    "otherJobType": "",
    "fieldJobDetails": [
      {
        "kva": "jk",
        "srNo": "k",
        "rating": "p",
        "note": "["
      },
      {
        "kva": "add2",
        "srNo": "add2",
        "rating": "add2",
        "note": "add2"
      },
      {
        "kva": "add",
        "srNo": "add",
        "rating": "add",
        "note": "addkk"
      }
    ],
    "execution": "Started",
    "jobCompletionCertificate": null,
    "delivery": true,
    "id": "1755383669192",
    "updatedAt": "2025-08-18T00:47:21.009Z"
  },
  {
    "location": "Site",
    "category": "Public",
    "orderNo": "345678",
    "date": "2025-08-08",
    "type": "Division",
    "dismental": "",
    "wind": "",
    "assemble": "",
    "testing": "",
    "siteLocation": "asadfrychgn",
    "client": "xchvgjbkn",
    "typeOfJob": "Filter",
    "otherJobType": "",
    "fieldJobDetails": [
      {
        "kva": "3",
        "srNo": "3",
        "rating": "3",
        "note": "3"
      },
      {
        "kva": "4",
        "srNo": "4",
        "rating": "4",
        "note": "4"
      }
    ],
    "execution": "Started",
    "jobCompletionCertificate": null,
    "delivery": false,
    "id": "1755383694816",
    "updatedAt": "2025-08-18T00:18:10.103Z"
  },
  {
    "location": "In House",
    "category": "Private",
    "orderNo": "newsatffsync",
    "date": "2025-08-02",
    "type": "Client",
    "dismental": "Started",
    "wind": "Started",
    "assemble": "Completed",
    "testing": "Started",
    "siteLocation": "",
    "client": "",
    "typeOfJob": "",
    "otherJobType": "",
    "fieldJobDetails": [
      {
        "kva": "",
        "srNo": "",
        "rating": "",
        "note": ""
      }
    ],
    "execution": "",
    "jobCompletionCertificate": null,
    "delivery": false,
    "id": "1755384997435"
  },
  {
    "location": "In House",
    "category": "WB",
    "orderNo": "admintestsync",
    "date": "2025-08-01",
    "type": "Division",
    "dismental": "Started",
    "wind": "Started",
    "assemble": "Completed",
    "testing": "Completed",
    "siteLocation": "",
    "client": "",
    "typeOfJob": "",
    "otherJobType": "",
    "fieldJobDetails": [
      {
        "kva": "",
        "srNo": "",
        "rating": "",
        "note": ""
      }
    ],
    "execution": "",
    "jobCompletionCertificate": null,
    "delivery": true,
    "id": "1755385160246",
    "updatedAt": "2025-08-17T00:20:07.511Z"
  },
  {
    "location": "Site",
    "category": "Private",
    "orderNo": "wertyui",
    "date": "2025-08-22",
    "type": "Division",
    "dismental": "",
    "wind": "",
    "assemble": "",
    "testing": "",
    "siteLocation": "3ertyu1",
    "client": "3213124",
    "typeOfJob": "Maintain",
    "otherJobType": "",
    "fieldJobDetails": [
      {
        "kva": "kva2",
        "srNo": "srno2",
        "rating": "rating2",
        "note": "note2"
      },
      {
        "kva": "werty",
        "srNo": "ergh",
        "rating": "sdfgh",
        "note": "dfg"
      }
    ],
    "execution": "Started",
    "jobCompletionCertificate": null,
    "delivery": true,
    "id": "1755391121583",
    "updatedAt": "2025-08-17T22:40:08.671Z"
  },
  {
    "location": "In House",
    "category": "WB",
    "orderNo": "pizza",
    "date": "2025-07-28",
    "type": "Client",
    "dismental": "Completed",
    "wind": "Started",
    "assemble": "Started",
    "testing": "Completed",
    "siteLocation": "",
    "client": "",
    "typeOfJob": "",
    "otherJobType": "",
    "fieldJobDetails": [
      {
        "kva": "",
        "srNo": "",
        "rating": "",
        "note": ""
      }
    ],
    "execution": "",
    "jobCompletionCertificate": null,
    "delivery": true,
    "id": "1755437063776"
  },
  {
    "location": "In House",
    "category": "WB",
    "orderNo": "fal",
    "date": "2025-07-31",
    "type": "Division",
    "dismental": "Completed",
    "wind": "Started",
    "assemble": "Started",
    "testing": "Started",
    "siteLocation": "",
    "client": "",
    "typeOfJob": "",
    "otherJobType": "",
    "fieldJobDetails": [
      {
        "kva": "",
        "srNo": "",
        "rating": "",
        "note": ""
      }
    ],
    "execution": "",
    "jobCompletionCertificate": null,
    "delivery": true,
    "id": "1755886336453",
    "updatedAt": "2025-08-22T18:12:28.852Z"
  },
  {
    "location": "In House",
    "category": "Private",
    "orderNo": "sample",
    "date": "2025-09-04",
    "type": "Client",
    "dismental": "Started",
    "wind": "Completed",
    "assemble": "Started",
    "testing": "Started",
    "siteLocation": "",
    "client": "",
    "typeOfJob": "",
    "otherJobType": "",
    "fieldJobDetails": [
      {
        "kva": "",
        "srNo": "",
        "rating": "",
        "note": ""
      }
    ],
    "execution": "",
    "jobCompletionCertificate": null,
    "delivery": false,
    "id": "1756760318112"
  },
  {
    "location": "In House",
    "category": "Private",
    "orderNo": "asfdasf",
    "date": "2025-09-03",
    "type": "Division",
    "dismental": "Started",
    "wind": "Started",
    "assemble": "Completed",
    "testing": "Completed",
    "siteLocation": "",
    "client": "",
    "typeOfJob": "",
    "otherJobType": "",
    "fieldJobDetails": [
      {
        "kva": "",
        "srNo": "",
        "rating": "",
        "note": ""
      }
    ],
    "execution": "",
    "jobCompletionCertificate": null,
    "delivery": false,
    "id": "1756760842360"
  }
]